icebridge/__init__.py
icebridge/client.py
icebridge/gateway.py
icebridge/version.py
icebridge/jars/app-uber.jar
icebridge-0.0.4.dist-info/LICENSE
icebridge-0.0.4.dist-info/METADATA
icebridge-0.0.4.dist-info/WHEEL
icebridge-0.0.4.dist-info/top_level.txt
icebridge-0.0.4.dist-info/RECORD
