Metadata-Version: 2.1
Name: icebridge
Version: 0.0.4
Summary: A Python Bridge to Apache Iceberg using Py4J
Author-email: "Eventual Inc." <team@eventualcomputing.com>
License: Apache License
Keywords: Iceberg,Data Warehouse
License-File: LICENSE
Requires-Dist: py4j (==0.10.9.5)
Requires-Dist: fsspec
Requires-Dist: s3fs
Requires-Dist: pyarrow (>=6)
Requires-Dist: numpy (>=1.20)
Requires-Dist: importlib-metadata ; python_version < "3.8"
Provides-Extra: test
Requires-Dist: pytest ; extra == 'test'
